felia/__init__.py
felia/__main__.py
felia/cobra.py
felia/django.py
felia/docker.py
felia/git.py
felia/go.py
felia/linux.py
felia/npm.py
felia/pip.py
felia/protoc.py
felia/python.py
felia/sphinx.py
felia/ssh.py
felia/supervisor.py
felia/telnet.py
felia/_internal/__init__.py
felia/_internal/base.py
felia/_internal/configuration.py
felia-0.5.0.dist-info/LICENSE
felia-0.5.0.dist-info/METADATA
felia-0.5.0.dist-info/WHEEL
felia-0.5.0.dist-info/top_level.txt
felia-0.5.0.dist-info/RECORD
