Metadata-Version: 2.1
Name: felia
Version: 0.5.0
Summary: A small example package
Home-page: https://gitee.com/luzhenxiong/felia
Author: paradox丶
Author-email: 397132445@qq.com
License: UNKNOWN
Project-URL: Bug Tracker, https://gitee.com/luzhenxiong/felia/issues
Platform: UNKNOWN
Classifier: Programming Language :: Python :: 3
Classifier: License :: OSI Approved :: MIT License
Classifier: Operating System :: OS Independent
Requires-Python: >=3.7
License-File: LICENSE
